Workbook

Sheet January
B2: January
B4: Income | C4: Goal | D4: Actual | F4: Juan's Spending Record
B5: Job | C5: 41000 | D5: 41000 | F5: Date | G5: Store | H5: Details | I5: Amount | J5: Expense Category | K5: Payment Method
B6: Other | C6: 0 | D6: 750 | F6: 44929 | G6: My Boss | H6: paycheck | I6: 41000 | J6: Income Job | K6: Cash
B7: Total Income: | C7: =SUM(C5:C6) -> 41000 | D7: =SUM(D5:D6) -> 41750 | F7: 44929 | G7: Market | H7: groceries | I7: 1080 | J7: Groceries | K7: Cash
F8: 44929 | G8: Bus | H8: going to work | I8: 100 | J8: Transportation | K8: Cash
B9: Expenses | C9: Goal | D9: Actual | F9: 44929 | G9: Landlord | H9: rent | I9: 10500 | J9: Housing | K9: Cash
B10: Tithing | C10: 4100 | D10: =D7*0.1 -> 4175 | F10: 44929 | G10: Utilities Office | H10: pay water and electricity | I10: 3474.18 | J10: Utilities | K10: Cash
B11: Fast Offering | C11: 300 | D11: 300 | F11: 44929 | G11: Put in Safe Place | H11: save money for tuition | I11: 680 | J11: Tutition | K11: Cash
B12: Taxes | C12: 3933.31 | D12: 3933.31 | F12: 44931 | G12: Bus | H12: going to church | I12: 100 | J12: Transportation | K12: Cash
B13: Tuition | C13: 680 | D13: 680 | F13: 44931 | G13: The Church of Jesus Christ | H13: tithing | I13: 4100 | J13: Tithing | K13: Cash
B14: Housing | C14: 10500 | D14: 10500 | F14: 44931 | G14: The Church of Jesus Christ | H14: fast offering | I14: 300 | J14: Fast Offering | K14: Cash
B15: Utilities | C15: 3300 | D15: 3474.18 | F15: 44932 | G15: Bus | H15: going to work | I15: 500 | J15: Transportation | K15: Cash
B16: Cell Phone | C16: 3626.64 | D16: =3345.97 -> 3345.97 | F16: 44932 | G16: Street Vendor | H16: lunch | I16: 150 | J16: Other | K16: Cash
B17: Internet | C17: 5400 | D17: 5565.13 | F17: 44936 | G17: Market | H17: groceries | I17: 1600 | J17: Groceries | K17: Cash
B18: Transportation | C18: 2500 | D18: =SUMIF($J$6:$J$36,B18,$I$6:$I$36) -> 2400 | F18: 44937 | G18: Tax Office | H18: pay taxes | I18: 3933.31 | J18: Taxes | K18: Cash
B19: Groceries | C19: 5000 | D19: =SUMIF($J$6:$J$36,B19,$I$6:$I$36) -> 5200 | F19: 44937 | G19: Street Vendor | H19: sweets | I19: 150 | J19: Other | K19: Cash
B20: Other | C20: 1500 | D20: =SUMIF($J$6:$J$36,B20,$I$6:$I$36) -> 2070 | F20: 44938 | G20: Bus | H20: going to church | I20: 100 | J20: Transportation | K20: Cash
B21: Emergency Fund | C21: 160 | D21: 181 | F21: 44938 | G21: Friend | H21: paid for service | I21: 750 | J21: Other Income | K21: Cash
B22: Total Expenses: | C22: =SUM(C10:C21) -> 40999.95 | D22: =SUM(D10:D21) -> 41824.59 | F22: 44938 | G22: The Church of Jesus Christ | H22: tithing | I22: 75 | J22: Tithing | K22: Cash
F23: 44939 | G23: Bus | H23: going to work | I23: 400 | J23: Transportation | K23: Cash
B24: Cash Flow Summary | C24: Goal | D24: Actual | F24: 44943 | G24: Market | H24: groceries | I24: 1470 | J24: Groceries | K24: Cash
B25: Total Income | C25: =C7 -> 41000 | D25: =D7 -> 41750 | F25: 44944 | G25: Phone Place | H25: cell phone bill | I25: 3345.97 | J25: Cell Phone | K25: Cash
B26: Total Expenses | C26: =C22 -> 40999.95 | D26: =D22 -> 41824.59 | F26: 44944 | G26: Wireless | H26: internet for home | I26: 5565.13 | J26: Internet | K26: Cash
B27: Monthly Cash Flow: | C27: =C25-C26 -> 0.05 | D27: =D25-D26 -> -74.59 | F27: 44944 | G27: Tailor | H27: new pants | I27: 1200 | J27: Other | K27: Cash
F28: 44945 | G28: Bus | H28: going to church | I28: 100 | J28: Transportation | K28: Cash
F29: 44946 | G29: Bus | H29: going to work | I29: 500 | J29: Transportation | K29: Cash
F30: 44950 | G30: Market | H30: groceries | I30: 1050 | J30: Groceries | K30: Cash
F31: 44951 | G31: Bus | H31: going to movie | I31: 100 | J31: Transportation | K31: Cash
F32: 44951 | G32: Movie Theather | H32: movie with friend | I32: 370 | J32: Other | K32: Cash
F33: 44952 | G33: Bus | H33: going to church | I33: 100 | J33: Transportation | K33: Cash
F34: 44953 | G34: Bus | H34: going to work | I34: 400 | J34: Transportation | K34: Cash
F35: 44954 | G35: Street Vendor | H35: sweets | I35: 200 | J35: Other | K35: Cash
F36: 44954 | G36: Savings | H36: emergency fund deposit | I36: 181 | J36: Emergency Fund | K36: Cash

Sheet February
B2: February
B4: Income | C4: Goal | D4: Actual | F4: Juan's Spending Record
B5: Job | C5: 41000 | D5: 41000 | F5: Date | G5: Store | H5: Details | I5: Amount | J5: Expense Category | K5: Payment Method
B6: Other | C6: 0 | D6: 0 | F6: 44958 | G6: My Boss | H6: paycheck | I6: 41000 | J6: Income Job | K6: Cash
B7: Total Income: | C7: =SUM(C5:C6) -> 41000 | D7: =SUM(D5:D6) -> 41000 | F7: 45689 | G7: Landlord | H7: rent | I7: 10500 | J7: Housing | K7: Cash
F8: 45689 | G8: Utilities | H8: store | I8: 3611.39 | J8: Utilities | K8: Cash
B9: Expenses | C9: Goal | D9: Actual | F9: 45691 | G9: The Church of Jesus Christ | H9: Tithing | I9: 4100 | J9: Tithing | K9: Cash
B10: Tithing | C10: 4100 | D10: =SUMIF($J$6:$J$42,B10,$I$6:$I$42) -> 4100 | F10: 45691 | G10: The Church of Jesus Christ | H10: fast offering | I10: 300 | J10: Fast Offering | K10: Cash
B11: Fast Offering | C11: 300 | D11: =SUMIF($J$6:$J$42,B11,$I$6:$I$42) -> 300 | F11: 45692 | G11: Bus | H11: going to church | I11: 500 | J11: Transportation | K11: Cash
B12: Taxes | C12: 3933.31 | D12: =SUMIF($J$6:$J$42,B12,$I$6:$I$42) -> 0 | F12: 45692 | G12: Market | H12: groceries | I12: 1293.75 | J12: Groceries | K12: Cash
B13: Tuition | C13: 680 | D13: =SUMIF($J$6:$J$42,B13,$I$6:$I$42) -> 0
B14: Housing | C14: 10500 | D14: =SUMIF($J$6:$J$42,B14,$I$6:$I$42) -> 10500
B15: Utilities | C15: 3300 | D15: =SUMIF($J$6:$J$42,B15,$I$6:$I$42) -> 3611.39
B16: Cell Phone | C16: 3626.64 | D16: =SUMIF($J$6:$J$42,B16,$I$6:$I$42) -> 0
B17: Internet | C17: 5400 | D17: =SUMIF($J$6:$J$42,B17,$I$6:$I$42) -> 0
B18: Transportation | C18: 2500 | D18: =SUMIF($J$6:$J$42,B18,$I$6:$I$42) -> 500
B19: Groceries | C19: 5000 | D19: =SUMIF($J$6:$J$42,B19,$I$6:$I$42) -> 1293.75
B20: Other | C20: 1000 | D20: =SUMIF($J$6:$J$42,B20,$I$6:$I$42) -> 0
B21: Emergency Fund | C21: 500 | D21: =SUMIF($J$6:$J$42,B21,$I$6:$I$42) -> 0
B22: Total Expenses: | C22: =SUM(C10:C21) -> 40839.95 | D22: =SUM(D10:D21) -> 20305.14
B24: Cash Flow Summary | C24: Goal | D24: Actual
B25: Total Income | C25: =C7 -> 41000 | D25: =D7 -> 41000
B26: Total Expenses | C26: =C22 -> 40839.95 | D26: =D22 -> 20305.14
B27: Monthly Cash Flow: | C27: =C25-C26 -> 160.05 | D27: =D25-D26 -> 20694.86

Sheet How Did I Do
A1: 2025 Block 5
A3: January Tab, D18 | B3: =IF(January!D18-2400=0,"Correct","Error") -> Correct
A4: January Tab, D19 | B4: =IF(January!D19-5200=0,"Correct","Error") -> Correct
A5: January Tab, D20 | B5: =IF(January!D20-2070=0,"Correct","Error") -> Correct
A7: February Tab, D10 | B7: =IF(February!D10-4100=0,"Correct","Error") -> Correct
A8: February Tab, D11 | B8: =IF(February!D11-300=0,"Correct","Error") -> Correct
A9: February Tab, D12 | B9: =IF(February!D12-0=0,"Correct","Error") -> Correct
A10: February Tab, D13 | B10: =IF(February!D13-0=0,"Correct","Error") -> Correct
A11: February Tab, D14 | B11: =IF(February!D14-10500=0,"Correct","Error") -> Correct
A12: February Tab, D15 | B12: =IF(February!D15-3611.39=0,"Correct","Error") -> Correct
A13: February Tab, D16 | B13: =IF(February!D16-0=0,"Correct","Error") -> Correct
A14: February Tab, D17 | B14: =IF(February!D17-0=0,"Correct","Error") -> Correct
A15: February Tab, D18 | B15: =IF(February!D18-500=0,"Correct","Error") -> Correct
A16: February Tab, D19 | B16: =IF(February!D19-1293.75=0,"Correct","Error") -> Correct
A17: February Tab, D20 | B17: =IF(February!D20-0=0,"Correct","Error") -> Correct
A18: February Tab, D21 | B18: =IF(February!D21-0=0,"Correct","Error") -> Correct
A20: February Tab, C10 | B20: =IF(February!C10-4100=0,"Correct","Error") -> Correct
A21: February Tab, C11 | B21: =IF(February!C11-300=0,"Correct","Error") -> Correct
A22: February Tab, C12 | B22: =IF(February!C12-3933.31=0,"Correct","Error") -> Correct
A23: February Tab, C13 | B23: =IF(February!C13-680=0,"Correct","Error") -> Correct
A24: February Tab, C14 | B24: =IF(February!C14-10500=0,"Correct","Error") -> Correct
A25: February Tab, C15 | B25: Provide explanation in the word document if you changed this cell
A26: February Tab, C16 | B26: Provide explanation in the word document if you changed this cell
A27: February Tab, C17 | B27: Provide explanation in the word document if you changed this cell
A28: February Tab, C18 | B28: Provide explanation in the word document if you changed this cell
A29: February Tab, C19 | B29: Provide explanation in the word document if you changed this cell
A30: February Tab, C20 | B30: Provide explanation in the word document if you changed this cell
A31: February Tab, C21 | B31: =IF(AND(February!C21>=400,February!C21<=600),"Correct","Error") -> Correct
A33: February Tab, C27 | B33: =IF((February!C25-February!C26)>=0,"Correct","Error") -> Correct

Sheet Your Budget
B2: [Month] | C2: Optional: You can use this sheet to make a budget for yourself.
B4: Income | C4: Goal | D4: Actual | F4: My Spending Record
B5: Job | F5: Date | G5: Store | H5: Details | I5: Amount | J5: Expense Category | K5: Payment Method
B6: Other
B7: Total Income: | C7: =SUM(C5:C6) -> 0 | D7: =SUM(D5:D6) -> 0
B9: Expenses | C9: Goal | D9: Actual
B10: Tithing
B11: Fast Offering
B12: Taxes
B13: Tuition
B14: Housing
B15: Utilities
B16: Cell Phone
B17: Internet
B18: Transportation
B19: Groceries
B20: Other
B21: Emergency Fund
B25: Total Expenses: | C25: =SUM(C10:C24) -> 0 | D25: =SUM(D10:D24) -> 0
B27: Cash Flow Summary | C27: Goal | D27: Actual
B28: Total Income | C28: =C7 -> 0 | D28: =D7 -> 0
B29: Total Expenses | C29: =C25 -> 0 | D29: =D25 -> 0
B30: Monthly Cash Flow: | C30: =C28-C29 -> 0 | D30: =D28-D29 -> 0
